envlicenses/__init__.py
envlicenses/permissive.txt
acellera_envlicenses-0.0.5.dist-info/METADATA
acellera_envlicenses-0.0.5.dist-info/WHEEL
acellera_envlicenses-0.0.5.dist-info/entry_points.txt
acellera_envlicenses-0.0.5.dist-info/top_level.txt
acellera_envlicenses-0.0.5.dist-info/RECORD
