Metadata-Version: 2.1
Name: acellera-envlicenses
Version: 0.0.5
Summary: envlicenses
Home-page: https://www.htmd.org
Maintainer: Acellera Ltd
Maintainer-email: info@acellera.com
